arm_pyart-2.2.0.data/scripts/anytocfradial
arm_pyart-2.2.0.data/scripts/check_cfradial
arm_pyart-2.2.0.data/scripts/convert_legacy_grid
arm_pyart-2.2.0.data/scripts/radar_info
arm_pyart-2.2.0.data/scripts/radar_plot
arm_pyart-2.2.0.dist-info/licenses/LICENSE.txt
pyart/__init__.py
pyart/_debug_info.py
pyart/config.py
pyart/default_config.py
pyart/exceptions.py
pyart/lazydict.py
pyart/__check_build/README
pyart/__check_build/__init__.py
pyart/__check_build/_check_build.c
pyart/__check_build/_check_build.cp310-win_amd64.pyd
pyart/__check_build/_check_build.pyx
pyart/aux_io/__init__.py
pyart/aux_io/arm_vpt.py
pyart/aux_io/d3r_gcpex_nc.py
pyart/aux_io/edge_netcdf.py
pyart/aux_io/gamic_hdf5.py
pyart/aux_io/gamicfile.py
pyart/aux_io/kazr_spectra.py
pyart/aux_io/noxp_iphex_nc.py
pyart/aux_io/odim_h5.py
pyart/aux_io/pattern.py
pyart/aux_io/radx.py
pyart/aux_io/radx_grid.py
pyart/aux_io/rainbow_wrl.py
pyart/aux_io/rxm25.py
pyart/aux_io/sinarame_h5.py
pyart/bridge/__init__.py
pyart/bridge/wradlib_bridge.py
pyart/core/__init__.py
pyart/core/grid.py
pyart/core/radar.py
pyart/core/radar_spectra.py
pyart/core/transforms.py
pyart/core/wind_profile.py
pyart/correct/__init__.pxd
pyart/correct/__init__.py
pyart/correct/_common_dealias.py
pyart/correct/_fast_edge_finder.c
pyart/correct/_fast_edge_finder.cp310-win_amd64.pyd
pyart/correct/_fast_edge_finder.pyx
pyart/correct/_fourdd_h.pxd
pyart/correct/_fourdd_interface.pyx
pyart/correct/_unwrap_1d.c
pyart/correct/_unwrap_1d.cp310-win_amd64.pyd
pyart/correct/_unwrap_1d.pyx
pyart/correct/_unwrap_2d.c
pyart/correct/_unwrap_2d.cp310-win_amd64.pyd
pyart/correct/_unwrap_2d.pyx
pyart/correct/_unwrap_3d.c
pyart/correct/_unwrap_3d.cp310-win_amd64.pyd
pyart/correct/_unwrap_3d.pyx
pyart/correct/attenuation.py
pyart/correct/bias_and_noise.py
pyart/correct/dealias.py
pyart/correct/despeckle.py
pyart/correct/phase_proc.py
pyart/correct/rebuild_fast_edge_finder.sh
pyart/correct/rebuild_fourdd_interface.sh
pyart/correct/region_dealias.py
pyart/correct/unwrap.py
pyart/correct/unwrap_2d_ljmu.c
arm_pyart-2.2.0.dist-info/METADATA
arm_pyart-2.2.0.dist-info/WHEEL
arm_pyart-2.2.0.dist-info/top_level.txt
arm_pyart-2.2.0.dist-info/RECORD
