Metadata-Version: 2.4
Name: arm_pyart
Version: 2.2.0
Summary: Py-ART: Python ARM Radar Toolkit
Author: Jonathan Helmus
Author-email: Scott Collis <scollis@anl.gov>
Maintainer-email: Py-ART Developers <zsherman@anl.gov>, scollis@anl.gov, mgrover@anl.gov
License-Expression: BSD-3-Clause
Project-URL: Homepage, https://github.com/ARM-DOE/pyart
Platform: Linux
Platform: Mac OS-X
Platform: Unix
Platform: Windows
Classifier: Development Status :: 5 - Production/Stable
Classifier: Intended Audience :: Science/Research
Classifier: Intended Audience :: Developers
Classifier: Programming Language :: Python
Classifier: Programming Language :: Python :: 3
Classifier: Programming Language :: Python :: 3.10
Classifier: Programming Language :: Python :: 3.11
Classifier: Programming Language :: Python :: 3.12
Classifier: Programming Language :: Python :: 3.13
Classifier: Programming Language :: C
Classifier: Programming Language :: Cython
Classifier: Topic :: Scientific/Engineering
Classifier: Topic :: Scientific/Engineering :: Atmospheric Science
Classifier: Operating System :: POSIX :: Linux
Classifier: Operating System :: MacOS :: MacOS X
Classifier: Operating System :: Microsoft :: Windows
Classifier: Framework :: Matplotlib
Requires-Python: >=3.10
License-File: LICENSE.txt
Requires-Dist: cartopy>=0.22.0
Requires-Dist: cftime>=1.5.1.1
Requires-Dist: fsspec>=2021.11.0
Requires-Dist: matplotlib>=3.5.0
Requires-Dist: mda-xdrlib>=0.2.0
Requires-Dist: netcdf4>=1.7.2
Requires-Dist: numpy>=1.21.2
Requires-Dist: open-radar-data>=0.5.0
Requires-Dist: pandas>=1.3.4
Requires-Dist: pint>=0.18.0
Requires-Dist: pooch>=1.5.2
Requires-Dist: s3fs>=2021.11.0
Requires-Dist: scipy>=1.7.3
Requires-Dist: xarray>=2024.10.0
Requires-Dist: xradar>=0.8.0
Dynamic: description
Dynamic: license-file
